postal_py/__init__.py
postal_py/api/__init__.py
postal_py/api/async_wrapper.py
postal_py/api/base.py
postal_py/api/exceptions.py
postal_py/api/schemas.py
postal_py/api/wrapper.py
postal_py/smtp/__init__.py
postal_py/smtp/async_wrapper.py
postal_py/smtp/base.py
postal_py/smtp/schemas.py
postal_py/smtp/wrapper.py
postal_py-0.0.5.dist-info/licenses/LICENSE
postal_py-0.0.5.dist-info/METADATA
postal_py-0.0.5.dist-info/WHEEL
postal_py-0.0.5.dist-info/top_level.txt
postal_py-0.0.5.dist-info/RECORD
