Metadata-Version: 2.4
Name: postal_py
Version: 0.0.5
Summary: PostalPy is a library for interacting with the Postal server.
Author-email: regenara <jakebv.22@gmail.com>
License: MIT License
Project-URL: repository, https://github.com/regenara/postal_py
Project-URL: homepage, https://github.com/regenara/postal_py
Requires-Python: >=3.10
License-File: LICENSE
Requires-Dist: pydantic<3.0.0,>=2.0.0
Requires-Dist: niquests<4.0.0,>=3.0.0
Provides-Extra: smtp
Requires-Dist: aiosmtplib<5.0.0,>=4.0.0; extra == "smtp"
Dynamic: license-file
